titifel_pypi/__init__.py
titifel_pypi/collect_info.py
titifel_pypi-5.0.0.dist-info/METADATA
titifel_pypi-5.0.0.dist-info/WHEEL
titifel_pypi-5.0.0.dist-info/top_level.txt
titifel_pypi-5.0.0.dist-info/RECORD
