Metadata-Version: 2.4
Name: titifel_pypi
Version: 5.0.0
Requires-Dist: requests>=2.0
Dynamic: requires-dist
